MANIFEST.in
README.md
setup.py
backend/__init__.py
backend/db.sqlite3
backend/manage.py
backend/requirements.txt
backend/backend/__init__.py
backend/backend/asgi.py
backend/backend/blog_routers.py
backend/backend/create_blog_routers.py
backend/backend/message_routers.py
backend/backend/password_routers.py
backend/backend/serializers.py
backend/backend/settings.py
backend/backend/urls.py
backend/backend/users_routers.py
backend/backend/utils.py
backend/backend/views.py
backend/backend/wsgi.py
backend/blog/__init__.py
backend/blog/admin.py
backend/blog/apps.py
backend/blog/models.py
backend/blog/serializers.py
backend/blog/tests.py
backend/blog/views.py
backend/blog/migrations/0001_initial.py
backend/blog/migrations/0002_login.py
backend/blog/migrations/0003_auto_20220505_2355.py
backend/blog/migrations/0004_post_username.py
backend/blog/migrations/0005_alertmessage.py
backend/blog/migrations/0006_alertmessage_category.py
backend/blog/migrations/__init__.py
personal_site_msilvasy.egg-info/PKG-INFO
personal_site_msilvasy.egg-info/SOURCES.txt
personal_site_msilvasy.egg-info/dependency_links.txt
personal_site_msilvasy.egg-info/entry_points.txt
personal_site_msilvasy.egg-info/requires.txt
personal_site_msilvasy.egg-info/top_level.txt