Metadata-Version: 1.0
Name: personal-site-msilvasy
Version: 1.0.5
Summary: Vue.js, Nuxt.js, Django, Django Rest Framework and PostgreSQL personal project
Home-page: http://mikesilvasy.com
Author: Mike Silvasy
Author-email: mike.silvasy@gmail.com
License: UNKNOWN
Platform: UNKNOWN
